{
  "updated_utc": "2026-01-21T21:03:30.644095+00:00",
  "params": {
    "tf": "1d",
    "lookback_days": 520,
    "max_bars": 320,
    "sma_fast": 20,
    "sma_slow": 50,
    "min_pullback_pct": 3.0,
    "swing_window": 80,
    "support_lookback": 80,
    "rebound_bars": 4,
    "support_tolerance_pct": 1.0,
    "uptrend_window_min": 30,
    "uptrend_window_max": 50,
    "pivot_strength": 2,
    "min_hh": 3,
    "min_hl": 3,
    "corr_bars_min": 3,
    "corr_bars_max": 12,
    "only_actionable": false,
    "only_watchlist": true
  },
  "count": 22,
  "data": [
    {
      "ticker": "MLAB",
      "tf": "1d",
      "bars_used": 320,
      "close": 82.87000274658203,
      "sma_fast": 20,
      "sma_slow": 50,
      "sma_fast_now": 83.19000015258788,
      "sma_slow_now": 79.45760681152343,
      "trend_ok": true,
      "recent_swing_high": 89.94999694824219,
      "recent_swing_high_date": "2026-01-07",
      "resistance_level": 89.94999694824219,
      "pullback_from_swing_high_pct": 7.871033287231828,
      "had_correction": true,
      "bars_since_swing_high": 8,
      "correction_age_ok": true,
      "anchor_support_close": 76.97000122070312,
      "anchor_support_date": "2025-12-30",
      "support_level": 76.97000122070312,
      "support_tolerance_pct": 1.0,
      "support_floor": 76.97000122070312,
      "support_floor_adj": 76.2003012084961,
      "correction_close_low": 81.19000244140625,
      "support_held": true,
      "close_above_sma_fast": false,
      "rebound_ok": false,
      "uptrend_window_used": 50,
      "uptrend_hh_count": 4,
      "uptrend_hl_count": 5,
      "uptrend_pivot_highs": 7,
      "uptrend_pivot_lows": 6,
      "uptrend_overall_up": true,
      "uptrend_ok": true,
      "uptrend_actionable": true,
      "watchlist_correction": true,
      "actionable_after_correction": true,
      "dist_to_support": 0.07665326013132431,
      "actionable_reason": "watchlist_correction",
      "priceQuality": {
        "quality_n_bars": 50,
        "long_wick_count": 23,
        "max_long_wicks_allowed": 6,
        "gap_thresh_pct": 2.5,
        "gap_count": 1,
        "max_gap_count_allowed": 2,
        "max_gap_pct": 3.021761451575497,
        "max_gap_pct_allowed": 6.0,
        "avg_volume_50": 136680,
        "price_quality_ok": false
      },
      "priceQualityOk": false,
      "avgVolume50": 136680,
      "rank_score": 3.2604500685918585
    },
    {
      "ticker": "NVCR",
      "tf": "1d",
      "bars_used": 320,
      "close": 13.015000343322754,
      "sma_fast": 20,
      "sma_slow": 50,
      "sma_fast_now": 13.637750101089477,
      "sma_slow_now": 12.689700088500977,
      "trend_ok": true,
      "recent_swing_high": 15.149999618530273,
      "recent_swing_high_date": "2026-01-09",
      "resistance_level": 15.149999618530273,
      "pullback_from_swing_high_pct": 14.092404811655298,
      "had_correction": true,
      "bars_since_swing_high": 6,
      "correction_age_ok": true,
      "anchor_support_close": 12.880000114440918,
      "anchor_support_date": "2025-12-31",
      "support_level": 12.880000114440918,
      "support_tolerance_pct": 1.0,
      "support_floor": 12.880000114440918,
      "support_floor_adj": 12.751200113296509,
      "correction_close_low": 13.015000343322754,
      "support_held": true,
      "close_above_sma_fast": false,
      "rebound_ok": false,
      "uptrend_window_used": 50,
      "uptrend_hh_count": 4,
      "uptrend_hl_count": 3,
      "uptrend_pivot_highs": 6,
      "uptrend_pivot_lows": 5,
      "uptrend_overall_up": true,
      "uptrend_ok": true,
      "uptrend_actionable": true,
      "watchlist_correction": true,
      "actionable_after_correction": true,
      "dist_to_support": 0.010481384136827384,
      "actionable_reason": "watchlist_correction",
      "priceQuality": {
        "quality_n_bars": 50,
        "long_wick_count": 19,
        "max_long_wicks_allowed": 6,
        "gap_thresh_pct": 2.5,
        "gap_count": 3,
        "max_gap_count_allowed": 2,
        "max_gap_pct": 5.4644866511284516,
        "max_gap_pct_allowed": 6.0,
        "avg_volume_50": 1593998,
        "price_quality_ok": false
      },
      "priceQualityOk": false,
      "avgVolume50": 1593998,
      "rank_score": 3.2395186158631732
    },
    {
      "ticker": "NNNN",
      "tf": "1d",
      "bars_used": 231,
      "close": 30.809999465942383,
      "sma_fast": 20,
      "sma_slow": 50,
      "sma_fast_now": 33.68549976348877,
      "sma_slow_now": 29.806699905395508,
      "trend_ok": true,
      "recent_swing_high": 43.0,
      "recent_swing_high_date": "2026-01-14",
      "resistance_level": 43.0,
      "pullback_from_swing_high_pct": 28.348838451296782,
      "had_correction": true,
      "bars_since_swing_high": 3,
      "correction_age_ok": true,
      "anchor_support_close": 30.149999618530273,
      "anchor_support_date": "2026-01-08",
      "support_level": 30.149999618530273,
      "support_tolerance_pct": 1.0,
      "support_floor": 30.149999618530273,
      "support_floor_adj": 29.84849962234497,
      "correction_close_low": 30.809999465942383,
      "support_held": true,
      "close_above_sma_fast": false,
      "rebound_ok": false,
      "uptrend_window_used": 50,
      "uptrend_hh_count": 4,
      "uptrend_hl_count": 3,
      "uptrend_pivot_highs": 7,
      "uptrend_pivot_lows": 4,
      "uptrend_overall_up": true,
      "uptrend_ok": true,
      "uptrend_actionable": true,
      "watchlist_correction": true,
      "actionable_after_correction": true,
      "dist_to_support": 0.021890542479691164,
      "actionable_reason": "watchlist_correction",
      "priceQuality": {
        "quality_n_bars": 50,
        "long_wick_count": 10,
        "max_long_wicks_allowed": 6,
        "gap_thresh_pct": 2.5,
        "gap_count": 29,
        "max_gap_count_allowed": 2,
        "max_gap_pct": 9.816479361722843,
        "max_gap_pct_allowed": 6.0,
        "avg_volume_50": 31756,
        "price_quality_ok": false
      },
      "priceQualityOk": false,
      "avgVolume50": 31756,
      "rank_score": 3.228109457520309
    },
    {
      "ticker": "OCGN",
      "tf": "1d",
      "bars_used": 320,
      "close": 1.6699999570846558,
      "sma_fast": 20,
      "sma_slow": 50,
      "sma_fast_now": 1.5415000021457672,
      "sma_slow_now": 1.3708000040054322,
      "trend_ok": true,
      "recent_swing_high": 1.9600000381469727,
      "recent_swing_high_date": "2026-01-14",
      "resistance_level": 1.9600000381469727,
      "pullback_from_swing_high_pct": 14.795922215210231,
      "had_correction": true,
      "bars_since_swing_high": 3,
      "correction_age_ok": true,
      "anchor_support_close": 1.475000023841858,
      "anchor_support_date": "2026-01-09",
      "support_level": 1.475000023841858,
      "support_tolerance_pct": 1.0,
      "support_floor": 1.475000023841858,
      "support_floor_adj": 1.4602500236034393,
      "correction_close_low": 1.6200000047683716,
      "support_held": true,
      "close_above_sma_fast": true,
      "rebound_ok": false,
      "uptrend_window_used": 50,
      "uptrend_hh_count": 4,
      "uptrend_hl_count": 5,
      "uptrend_pivot_highs": 7,
      "uptrend_pivot_lows": 8,
      "uptrend_overall_up": true,
      "uptrend_ok": true,
      "uptrend_actionable": true,
      "watchlist_correction": true,
      "actionable_after_correction": true,
      "dist_to_support": 0.13220334243445733,
      "actionable_reason": "watchlist_correction",
      "priceQuality": {
        "quality_n_bars": 50,
        "long_wick_count": 11,
        "max_long_wicks_allowed": 6,
        "gap_thresh_pct": 2.5,
        "gap_count": 9,
        "max_gap_count_allowed": 2,
        "max_gap_pct": 5.645165476913102,
        "max_gap_pct_allowed": 6.0,
        "avg_volume_50": 4405866,
        "price_quality_ok": false
      },
      "priceQualityOk": false,
      "avgVolume50": 4405866,
      "rank_score": 3.2177966575655432
    },
    {
      "ticker": "NUTX",
      "tf": "1d",
      "bars_used": 320,
      "close": 153.75999450683594,
      "sma_fast": 20,
      "sma_slow": 50,
      "sma_fast_now": 171.0217498779297,
      "sma_slow_now": 151.55329986572266,
      "trend_ok": true,
      "recent_swing_high": 192.0,
      "recent_swing_high_date": "2026-01-09",
      "resistance_level": 192.0,
      "pullback_from_swing_high_pct": 19.916669527689614,
      "had_correction": true,
      "bars_since_swing_high": 6,
      "correction_age_ok": true,
      "anchor_support_close": 146.82000732421875,
      "anchor_support_date": "2026-01-02",
      "support_level": 146.82000732421875,
      "support_tolerance_pct": 1.0,
      "support_floor": 146.82000732421875,
      "support_floor_adj": 145.35180725097655,
      "correction_close_low": 152.77000427246094,
      "support_held": true,
      "close_above_sma_fast": false,
      "rebound_ok": false,
      "uptrend_window_used": 50,
      "uptrend_hh_count": 4,
      "uptrend_hl_count": 3,
      "uptrend_pivot_highs": 7,
      "uptrend_pivot_lows": 5,
      "uptrend_overall_up": true,
      "uptrend_ok": true,
      "uptrend_actionable": true,
      "watchlist_correction": true,
      "actionable_after_correction": true,
      "dist_to_support": 0.04726867481549566,
      "actionable_reason": "watchlist_correction",
      "priceQuality": {
        "quality_n_bars": 50,
        "long_wick_count": 11,
        "max_long_wicks_allowed": 6,
        "gap_thresh_pct": 2.5,
        "gap_count": 6,
        "max_gap_count_allowed": 2,
        "max_gap_pct": 21.784275478986785,
        "max_gap_pct_allowed": 6.0,
        "avg_volume_50": 180024,
        "price_quality_ok": false
      },
      "priceQualityOk": false,
      "avgVolume50": 180024,
      "rank_score": 3.2027313251845047
    },
    {
      "ticker": "OMCL",
      "tf": "1d",
      "bars_used": 320,
      "close": 49.060001373291016,
      "sma_fast": 20,
      "sma_slow": 50,
      "sma_fast_now": 47.97150001525879,
      "sma_slow_now": 42.5116000366211,
      "trend_ok": true,
      "recent_swing_high": 55.0,
      "recent_swing_high_date": "2026-01-13",
      "resistance_level": 55.0,
      "pullback_from_swing_high_pct": 10.799997503107244,
      "had_correction": true,
      "bars_since_swing_high": 4,
      "correction_age_ok": true,
      "anchor_support_close": 44.16999816894531,
      "anchor_support_date": "2026-01-02",
      "support_level": 44.16999816894531,
      "support_tolerance_pct": 1.0,
      "support_floor": 44.16999816894531,
      "support_floor_adj": 43.72829818725586,
      "correction_close_low": 49.060001373291016,
      "support_held": true,
      "close_above_sma_fast": true,
      "rebound_ok": false,
      "uptrend_window_used": 50,
      "uptrend_hh_count": 4,
      "uptrend_hl_count": 4,
      "uptrend_pivot_highs": 6,
      "uptrend_pivot_lows": 6,
      "uptrend_overall_up": true,
      "uptrend_ok": true,
      "uptrend_actionable": true,
      "watchlist_correction": true,
      "actionable_after_correction": true,
      "dist_to_support": 0.11070870289923913,
      "actionable_reason": "watchlist_correction",
      "priceQuality": {
        "quality_n_bars": 50,
        "long_wick_count": 19,
        "max_long_wicks_allowed": 6,
        "gap_thresh_pct": 2.5,
        "gap_count": 1,
        "max_gap_count_allowed": 2,
        "max_gap_pct": 5.163331345724681,
        "max_gap_pct_allowed": 6.0,
        "avg_volume_50": 528356,
        "price_quality_ok": false
      },
      "priceQualityOk": false,
      "avgVolume50": 528356,
      "rank_score": 3.1892912971007616
    },
    {
      "ticker": "NGEN",
      "tf": "1d",
      "bars_used": 320,
      "close": 5.239999771118164,
      "sma_fast": 20,
      "sma_slow": 50,
      "sma_fast_now": 5.433400011062622,
      "sma_slow_now": 4.253660006523132,
      "trend_ok": true,
      "recent_swing_high": 6.300000190734863,
      "recent_swing_high_date": "2026-01-08",
      "resistance_level": 6.300000190734863,
      "pullback_from_swing_high_pct": 16.825402976583966,
      "had_correction": true,
      "bars_since_swing_high": 7,
      "correction_age_ok": true,
      "anchor_support_close": 4.670000076293945,
      "anchor_support_date": "2025-12-31",
      "support_level": 4.670000076293945,
      "support_tolerance_pct": 1.0,
      "support_floor": 4.670000076293945,
      "support_floor_adj": 4.623300075531006,
      "correction_close_low": 5.239999771118164,
      "support_held": true,
      "close_above_sma_fast": false,
      "rebound_ok": false,
      "uptrend_window_used": 50,
      "uptrend_hh_count": 4,
      "uptrend_hl_count": 4,
      "uptrend_pivot_highs": 6,
      "uptrend_pivot_lows": 6,
      "uptrend_overall_up": true,
      "uptrend_ok": true,
      "uptrend_actionable": true,
      "watchlist_correction": true,
      "actionable_after_correction": true,
      "dist_to_support": 0.12205560717604175,
      "actionable_reason": "watchlist_correction",
      "priceQuality": {
        "quality_n_bars": 50,
        "long_wick_count": 14,
        "max_long_wicks_allowed": 6,
        "gap_thresh_pct": 2.5,
        "gap_count": 13,
        "max_gap_count_allowed": 2,
        "max_gap_pct": 9.578544446294751,
        "max_gap_pct_allowed": 6.0,
        "avg_volume_50": 153406,
        "price_quality_ok": false
      },
      "priceQualityOk": false,
      "avgVolume50": 153406,
      "rank_score": 3.177944392823959
    },
    {
      "ticker": "NCEW",
      "tf": "1d",
      "bars_used": 271,
      "close": 7.789999961853027,
      "sma_fast": 20,
      "sma_slow": 50,
      "sma_fast_now": 6.446750044822693,
      "sma_slow_now": 4.989540014266968,
      "trend_ok": true,
      "recent_swing_high": 10.145000457763672,
      "recent_swing_high_date": "2026-01-14",
      "resistance_level": 10.145000457763672,
      "pullback_from_swing_high_pct": 23.21340945932074,
      "had_correction": true,
      "bars_since_swing_high": 3,
      "correction_age_ok": true,
      "anchor_support_close": 6.255000114440918,
      "anchor_support_date": "2026-01-09",
      "support_level": 6.255000114440918,
      "support_tolerance_pct": 1.0,
      "support_floor": 6.255000114440918,
      "support_floor_adj": 6.192450113296509,
      "correction_close_low": 7.75,
      "support_held": true,
      "close_above_sma_fast": true,
      "rebound_ok": false,
      "uptrend_window_used": 50,
      "uptrend_hh_count": 5,
      "uptrend_hl_count": 5,
      "uptrend_pivot_highs": 8,
      "uptrend_pivot_lows": 8,
      "uptrend_overall_up": true,
      "uptrend_ok": true,
      "uptrend_actionable": true,
      "watchlist_correction": true,
      "actionable_after_correction": true,
      "dist_to_support": 0.24540364817392335,
      "actionable_reason": "watchlist_correction",
      "priceQuality": {
        "quality_n_bars": 50,
        "long_wick_count": 24,
        "max_long_wicks_allowed": 6,
        "gap_thresh_pct": 2.5,
        "gap_count": 17,
        "max_gap_count_allowed": 2,
        "max_gap_pct": 8.99182984371695,
        "max_gap_pct_allowed": 6.0,
        "avg_volume_50": 57855,
        "price_quality_ok": false
      },
      "priceQualityOk": false,
      "avgVolume50": 57855,
      "rank_score": 3.154596351826077
    },
    {
      "ticker": "LIND",
      "tf": "1d",
      "bars_used": 320,
      "close": 15.640000343322754,
      "sma_fast": 20,
      "sma_slow": 50,
      "sma_fast_now": 15.184499883651734,
      "sma_slow_now": 13.525999927520752,
      "trend_ok": true,
      "recent_swing_high": 17.190000534057617,
      "recent_swing_high_date": "2026-01-14",
      "resistance_level": 17.190000534057617,
      "pullback_from_swing_high_pct": 9.01687110284803,
      "had_correction": true,
      "bars_since_swing_high": 3,
      "correction_age_ok": true,
      "anchor_support_close": 13.90999984741211,
      "anchor_support_date": "2026-01-02",
      "support_level": 13.90999984741211,
      "support_tolerance_pct": 1.0,
      "support_floor": 13.90999984741211,
      "support_floor_adj": 13.770899848937988,
      "correction_close_low": 15.640000343322754,
      "support_held": true,
      "close_above_sma_fast": true,
      "rebound_ok": false,
      "uptrend_window_used": 50,
      "uptrend_hh_count": 3,
      "uptrend_hl_count": 4,
      "uptrend_pivot_highs": 6,
      "uptrend_pivot_lows": 6,
      "uptrend_overall_up": true,
      "uptrend_ok": true,
      "uptrend_actionable": true,
      "watchlist_correction": true,
      "actionable_after_correction": true,
      "dist_to_support": 0.1243709931623402,
      "actionable_reason": "watchlist_correction",
      "priceQuality": {
        "quality_n_bars": 50,
        "long_wick_count": 20,
        "max_long_wicks_allowed": 6,
        "gap_thresh_pct": 2.5,
        "gap_count": 1,
        "max_gap_count_allowed": 2,
        "max_gap_pct": 4.004926906120603,
        "max_gap_pct_allowed": 6.0,
        "avg_volume_50": 458266,
        "price_quality_ok": false
      },
      "priceQualityOk": false,
      "avgVolume50": 458266,
      "rank_score": 3.12562900683766
    },
    {
      "ticker": "KRYS",
      "tf": "1d",
      "bars_used": 320,
      "close": 274.80999755859375,
      "sma_fast": 20,
      "sma_slow": 50,
      "sma_fast_now": 259.53700103759763,
      "sma_slow_now": 235.1544009399414,
      "trend_ok": true,
      "recent_swing_high": 295.9800109863281,
      "recent_swing_high_date": "2026-01-14",
      "resistance_level": 295.9800109863281,
      "pullback_from_swing_high_pct": 7.152514575963124,
      "had_correction": true,
      "bars_since_swing_high": 3,
      "correction_age_ok": true,
      "anchor_support_close": 235.60499572753906,
      "anchor_support_date": "2026-01-05",
      "support_level": 235.60499572753906,
      "support_tolerance_pct": 1.0,
      "support_floor": 235.60499572753906,
      "support_floor_adj": 233.24894577026367,
      "correction_close_low": 274.80999755859375,
      "support_held": true,
      "close_above_sma_fast": true,
      "rebound_ok": false,
      "uptrend_window_used": 50,
      "uptrend_hh_count": 6,
      "uptrend_hl_count": 3,
      "uptrend_pivot_highs": 8,
      "uptrend_pivot_lows": 4,
      "uptrend_overall_up": true,
      "uptrend_ok": true,
      "uptrend_actionable": true,
      "watchlist_correction": true,
      "actionable_after_correction": true,
      "dist_to_support": 0.1664014029498448,
      "actionable_reason": "watchlist_correction",
      "priceQuality": {
        "quality_n_bars": 50,
        "long_wick_count": 18,
        "max_long_wicks_allowed": 6,
        "gap_thresh_pct": 2.5,
        "gap_count": 0,
        "max_gap_count_allowed": 2,
        "max_gap_pct": 2.3415453272570876,
        "max_gap_pct_allowed": 6.0,
        "avg_volume_50": 299486,
        "price_quality_ok": false
      },
      "priceQualityOk": false,
      "avgVolume50": 299486,
      "rank_score": 3.098850054646468
    },
    {
      "ticker": "MYFW",
      "tf": "1d",
      "bars_used": 320,
      "close": 26.3799991607666,
      "sma_fast": 20,
      "sma_slow": 50,
      "sma_fast_now": 26.29699993133545,
      "sma_slow_now": 25.00800006866455,
      "trend_ok": true,
      "recent_swing_high": 28.0,
      "recent_swing_high_date": "2026-01-13",
      "resistance_level": 28.0,
      "pullback_from_swing_high_pct": 5.785717282976423,
      "had_correction": true,
      "bars_since_swing_high": 4,
      "correction_age_ok": true,
      "anchor_support_close": 25.489999771118164,
      "anchor_support_date": "2026-01-06",
      "support_level": 25.489999771118164,
      "support_tolerance_pct": 1.0,
      "support_floor": 25.489999771118164,
      "support_floor_adj": 25.235099773406983,
      "correction_close_low": 26.3799991607666,
      "support_held": true,
      "close_above_sma_fast": true,
      "rebound_ok": false,
      "uptrend_window_used": 50,
      "uptrend_hh_count": 4,
      "uptrend_hl_count": 4,
      "uptrend_pivot_highs": 7,
      "uptrend_pivot_lows": 7,
      "uptrend_overall_up": true,
      "uptrend_ok": true,
      "uptrend_actionable": true,
      "watchlist_correction": true,
      "actionable_after_correction": true,
      "dist_to_support": 0.034915629566104,
      "actionable_reason": "watchlist_correction",
      "priceQuality": {
        "quality_n_bars": 50,
        "long_wick_count": 17,
        "max_long_wicks_allowed": 6,
        "gap_thresh_pct": 2.5,
        "gap_count": 4,
        "max_gap_count_allowed": 2,
        "max_gap_pct": 5.700265163943781,
        "max_gap_pct_allowed": 6.0,
        "avg_volume_50": 27130,
        "price_quality_ok": false
      },
      "priceQualityOk": false,
      "avgVolume50": 27130,
      "rank_score": 3.043656098731539
    },
    {
      "ticker": "LFST",
      "tf": "1d",
      "bars_used": 320,
      "close": 7.179999828338623,
      "sma_fast": 20,
      "sma_slow": 50,
      "sma_fast_now": 7.193500065803528,
      "sma_slow_now": 6.7780000114440915,
      "trend_ok": true,
      "recent_swing_high": 7.519999980926514,
      "recent_swing_high_date": "2026-01-13",
      "resistance_level": 7.519999980926514,
      "pullback_from_swing_high_pct": 4.521278636306597,
      "had_correction": true,
      "bars_since_swing_high": 4,
      "correction_age_ok": true,
      "anchor_support_close": 6.764999866485596,
      "anchor_support_date": "2026-01-02",
      "support_level": 6.764999866485596,
      "support_tolerance_pct": 1.0,
      "support_floor": 6.764999866485596,
      "support_floor_adj": 6.69734986782074,
      "correction_close_low": 7.179999828338623,
      "support_held": true,
      "close_above_sma_fast": false,
      "rebound_ok": false,
      "uptrend_window_used": 50,
      "uptrend_hh_count": 6,
      "uptrend_hl_count": 5,
      "uptrend_pivot_highs": 7,
      "uptrend_pivot_lows": 6,
      "uptrend_overall_up": true,
      "uptrend_ok": true,
      "uptrend_actionable": true,
      "watchlist_correction": true,
      "actionable_after_correction": true,
      "dist_to_support": 0.06134515447797326,
      "actionable_reason": "watchlist_correction",
      "priceQuality": {
        "quality_n_bars": 50,
        "long_wick_count": 26,
        "max_long_wicks_allowed": 6,
        "gap_thresh_pct": 2.5,
        "gap_count": 0,
        "max_gap_count_allowed": 2,
        "max_gap_pct": 2.4691334404499927,
        "max_gap_pct_allowed": 6.0,
        "avg_volume_50": 2279734,
        "price_quality_ok": false
      },
      "priceQualityOk": false,
      "avgVolume50": 2279734,
      "rank_score": 3.0407827091526864
    },
    {
      "ticker": "KYTX",
      "tf": "1d",
      "bars_used": 320,
      "close": 9.020000457763672,
      "sma_fast": 20,
      "sma_slow": 50,
      "sma_fast_now": 8.664499950408935,
      "sma_slow_now": 8.031999950408936,
      "trend_ok": true,
      "recent_swing_high": 9.779999732971191,
      "recent_swing_high_date": "2026-01-14",
      "resistance_level": 9.779999732971191,
      "pullback_from_swing_high_pct": 7.770953946402917,
      "had_correction": true,
      "bars_since_swing_high": 3,
      "correction_age_ok": true,
      "anchor_support_close": 7.769999980926514,
      "anchor_support_date": "2026-01-06",
      "support_level": 7.769999980926514,
      "support_tolerance_pct": 1.0,
      "support_floor": 7.769999980926514,
      "support_floor_adj": 7.692299981117248,
      "correction_close_low": 8.359999656677246,
      "support_held": true,
      "close_above_sma_fast": true,
      "rebound_ok": false,
      "uptrend_window_used": 50,
      "uptrend_hh_count": 3,
      "uptrend_hl_count": 3,
      "uptrend_pivot_highs": 6,
      "uptrend_pivot_lows": 5,
      "uptrend_overall_up": true,
      "uptrend_ok": true,
      "uptrend_actionable": true,
      "watchlist_correction": true,
      "actionable_after_correction": true,
      "dist_to_support": 0.16087522263907458,
      "actionable_reason": "watchlist_correction",
      "priceQuality": {
        "quality_n_bars": 50,
        "long_wick_count": 10,
        "max_long_wicks_allowed": 6,
        "gap_thresh_pct": 2.5,
        "gap_count": 5,
        "max_gap_count_allowed": 2,
        "max_gap_pct": 38.95216606272722,
        "max_gap_pct_allowed": 6.0,
        "avg_volume_50": 1612228,
        "price_quality_ok": false
      },
      "priceQualityOk": false,
      "avgVolume50": 1612228,
      "rank_score": 3.016220172001217
    },
    {
      "ticker": "NWTG",
      "tf": "1d",
      "bars_used": 320,
      "close": 1.7000000476837158,
      "sma_fast": 20,
      "sma_slow": 50,
      "sma_fast_now": 1.6407499969005586,
      "sma_slow_now": 1.5197599995136262,
      "trend_ok": true,
      "recent_swing_high": 1.840000033378601,
      "recent_swing_high_date": "2026-01-12",
      "resistance_level": 1.840000033378601,
      "pullback_from_swing_high_pct": 7.608694736696163,
      "had_correction": true,
      "bars_since_swing_high": 5,
      "correction_age_ok": true,
      "anchor_support_close": 1.4850000143051147,
      "anchor_support_date": "2025-12-29",
      "support_level": 1.4850000143051147,
      "support_tolerance_pct": 1.0,
      "support_floor": 1.4850000143051147,
      "support_floor_adj": 1.4701500141620636,
      "correction_close_low": 1.7000000476837158,
      "support_held": true,
      "close_above_sma_fast": true,
      "rebound_ok": false,
      "uptrend_window_used": 50,
      "uptrend_hh_count": 3,
      "uptrend_hl_count": 3,
      "uptrend_pivot_highs": 6,
      "uptrend_pivot_lows": 4,
      "uptrend_overall_up": true,
      "uptrend_ok": true,
      "uptrend_actionable": true,
      "watchlist_correction": true,
      "actionable_after_correction": true,
      "dist_to_support": 0.14478116586362955,
      "actionable_reason": "watchlist_correction",
      "priceQuality": {
        "quality_n_bars": 50,
        "long_wick_count": 19,
        "max_long_wicks_allowed": 6,
        "gap_thresh_pct": 2.5,
        "gap_count": 16,
        "max_gap_count_allowed": 2,
        "max_gap_pct": 8.888893892735743,
        "max_gap_pct_allowed": 6.0,
        "avg_volume_50": 101350,
        "price_quality_ok": false
      },
      "priceQualityOk": false,
      "avgVolume50": 101350,
      "rank_score": 3.016088307805987
    },
    {
      "ticker": "LITM",
      "tf": "1d",
      "bars_used": 320,
      "close": 3.5,
      "sma_fast": 20,
      "sma_slow": 50,
      "sma_fast_now": 3.5170000314712526,
      "sma_slow_now": 3.3490000057220457,
      "trend_ok": true,
      "recent_swing_high": 4.03000020980835,
      "recent_swing_high_date": "2026-01-12",
      "resistance_level": 4.03000020980835,
      "pullback_from_swing_high_pct": 13.151369285748851,
      "had_correction": true,
      "bars_since_swing_high": 5,
      "correction_age_ok": true,
      "anchor_support_close": 2.940000057220459,
      "anchor_support_date": "2025-12-31",
      "support_level": 2.940000057220459,
      "support_tolerance_pct": 1.0,
      "support_floor": 2.940000057220459,
      "support_floor_adj": 2.910600056648254,
      "correction_close_low": 3.5,
      "support_held": true,
      "close_above_sma_fast": false,
      "rebound_ok": false,
      "uptrend_window_used": 50,
      "uptrend_hh_count": 3,
      "uptrend_hl_count": 3,
      "uptrend_pivot_highs": 5,
      "uptrend_pivot_lows": 6,
      "uptrend_overall_up": true,
      "uptrend_ok": true,
      "uptrend_actionable": true,
      "watchlist_correction": true,
      "actionable_after_correction": true,
      "dist_to_support": 0.190476167306261,
      "actionable_reason": "watchlist_correction",
      "priceQuality": {
        "quality_n_bars": 50,
        "long_wick_count": 14,
        "max_long_wicks_allowed": 6,
        "gap_thresh_pct": 2.5,
        "gap_count": 13,
        "max_gap_count_allowed": 2,
        "max_gap_pct": 6.363637611557318,
        "max_gap_pct_allowed": 6.0,
        "avg_volume_50": 523204,
        "price_quality_ok": false
      },
      "priceQualityOk": false,
      "avgVolume50": 523204,
      "rank_score": 3.009523832693739
    },
    {
      "ticker": "KVHI",
      "tf": "1d",
      "bars_used": 320,
      "close": 7.260000228881836,
      "sma_fast": 20,
      "sma_slow": 50,
      "sma_fast_now": 7.120500016212463,
      "sma_slow_now": 6.508000020980835,
      "trend_ok": true,
      "recent_swing_high": 7.690000057220459,
      "recent_swing_high_date": "2026-01-12",
      "resistance_level": 7.690000057220459,
      "pullback_from_swing_high_pct": 5.591675229376344,
      "had_correction": true,
      "bars_since_swing_high": 5,
      "correction_age_ok": true,
      "anchor_support_close": 6.619999885559082,
      "anchor_support_date": "2025-12-29",
      "support_level": 6.619999885559082,
      "support_tolerance_pct": 1.0,
      "support_floor": 6.619999885559082,
      "support_floor_adj": 6.553799886703491,
      "correction_close_low": 7.260000228881836,
      "support_held": true,
      "close_above_sma_fast": true,
      "rebound_ok": false,
      "uptrend_window_used": 50,
      "uptrend_hh_count": 3,
      "uptrend_hl_count": 4,
      "uptrend_pivot_highs": 6,
      "uptrend_pivot_lows": 5,
      "uptrend_overall_up": true,
      "uptrend_ok": true,
      "uptrend_actionable": true,
      "watchlist_correction": true,
      "actionable_after_correction": true,
      "dist_to_support": 0.09667679069283,
      "actionable_reason": "watchlist_correction",
      "priceQuality": {
        "quality_n_bars": 50,
        "long_wick_count": 27,
        "max_long_wicks_allowed": 6,
        "gap_thresh_pct": 2.5,
        "gap_count": 2,
        "max_gap_count_allowed": 2,
        "max_gap_pct": 4.355721197565655,
        "max_gap_pct_allowed": 6.0,
        "avg_volume_50": 77104,
        "price_quality_ok": false
      },
      "priceQualityOk": false,
      "avgVolume50": 77104,
      "rank_score": 2.912490732244805
    },
    {
      "ticker": "NDAQ",
      "tf": "1d",
      "bars_used": 320,
      "close": 97.41000366210938,
      "sma_fast": 20,
      "sma_slow": 50,
      "sma_fast_now": 98.71400032043456,
      "sma_slow_now": 93.05218566894531,
      "trend_ok": true,
      "recent_swing_high": 101.22000122070312,
      "recent_swing_high_date": "2026-01-07",
      "resistance_level": 101.22000122070312,
      "pullback_from_swing_high_pct": 3.7640757880315743,
      "had_correction": true,
      "bars_since_swing_high": 8,
      "correction_age_ok": true,
      "anchor_support_close": 95.80000305175781,
      "anchor_support_date": "2026-01-02",
      "support_level": 95.80000305175781,
      "support_tolerance_pct": 1.0,
      "support_floor": 95.80000305175781,
      "support_floor_adj": 94.84200302124023,
      "correction_close_low": 97.41000366210938,
      "support_held": true,
      "close_above_sma_fast": false,
      "rebound_ok": false,
      "uptrend_window_used": 50,
      "uptrend_hh_count": 5,
      "uptrend_hl_count": 3,
      "uptrend_pivot_highs": 6,
      "uptrend_pivot_lows": 4,
      "uptrend_overall_up": true,
      "uptrend_ok": true,
      "uptrend_actionable": true,
      "watchlist_correction": true,
      "actionable_after_correction": true,
      "dist_to_support": 0.016805851347225204,
      "actionable_reason": "watchlist_correction",
      "priceQuality": {
        "quality_n_bars": 50,
        "long_wick_count": 12,
        "max_long_wicks_allowed": 6,
        "gap_thresh_pct": 2.5,
        "gap_count": 0,
        "max_gap_count_allowed": 2,
        "max_gap_pct": 2.2320476618383585,
        "max_gap_pct_allowed": 6.0,
        "avg_volume_50": 3255896,
        "price_quality_ok": false
      },
      "priceQualityOk": false,
      "avgVolume50": 3255896,
      "rank_score": 2.859601727455932
    },
    {
      "ticker": "ONDS",
      "tf": "1d",
      "bars_used": 320,
      "close": 13.130000114440918,
      "sma_fast": 20,
      "sma_slow": 50,
      "sma_fast_now": 11.364500045776367,
      "sma_slow_now": 9.106100015640259,
      "trend_ok": true,
      "recent_swing_high": 15.279999732971191,
      "recent_swing_high_date": "2026-01-12",
      "resistance_level": 15.279999732971191,
      "pullback_from_swing_high_pct": 14.070678377637686,
      "had_correction": true,
      "bars_since_swing_high": 5,
      "correction_age_ok": true,
      "anchor_support_close": 8.210000038146973,
      "anchor_support_date": "2025-12-29",
      "support_level": 8.210000038146973,
      "support_tolerance_pct": 1.0,
      "support_floor": 8.210000038146973,
      "support_floor_adj": 8.127900037765503,
      "correction_close_low": 12.15999984741211,
      "support_held": true,
      "close_above_sma_fast": true,
      "rebound_ok": false,
      "uptrend_window_used": 50,
      "uptrend_hh_count": 5,
      "uptrend_hl_count": 4,
      "uptrend_pivot_highs": 7,
      "uptrend_pivot_lows": 7,
      "uptrend_overall_up": true,
      "uptrend_ok": true,
      "uptrend_actionable": true,
      "watchlist_correction": true,
      "actionable_after_correction": true,
      "dist_to_support": 0.5992691904304068,
      "actionable_reason": "watchlist_correction",
      "priceQuality": {
        "quality_n_bars": 50,
        "long_wick_count": 16,
        "max_long_wicks_allowed": 6,
        "gap_thresh_pct": 2.5,
        "gap_count": 22,
        "max_gap_count_allowed": 2,
        "max_gap_pct": 14.700542815474932,
        "max_gap_pct_allowed": 6.0,
        "avg_volume_50": 104548670,
        "price_quality_ok": false
      },
      "priceQualityOk": false,
      "avgVolume50": 104548670,
      "rank_score": 2.8500000000000005
    },
    {
      "ticker": "OMER",
      "tf": "1d",
      "bars_used": 320,
      "close": 12.260000228881836,
      "sma_fast": 20,
      "sma_slow": 50,
      "sma_fast_now": 13.498999881744385,
      "sma_slow_now": 10.830599937438965,
      "trend_ok": true,
      "recent_swing_high": 13.260000228881836,
      "recent_swing_high_date": "2026-01-14",
      "resistance_level": 13.260000228881836,
      "pullback_from_swing_high_pct": 7.541477999539417,
      "had_correction": true,
      "bars_since_swing_high": 3,
      "correction_age_ok": true,
      "anchor_support_close": 8.600000381469727,
      "anchor_support_date": "2025-12-23",
      "support_level": 8.600000381469727,
      "support_tolerance_pct": 1.0,
      "support_floor": 8.600000381469727,
      "support_floor_adj": 8.514000377655028,
      "correction_close_low": 12.010000228881836,
      "support_held": true,
      "close_above_sma_fast": false,
      "rebound_ok": false,
      "uptrend_window_used": 50,
      "uptrend_hh_count": 4,
      "uptrend_hl_count": 4,
      "uptrend_pivot_highs": 8,
      "uptrend_pivot_lows": 6,
      "uptrend_overall_up": true,
      "uptrend_ok": true,
      "uptrend_actionable": true,
      "watchlist_correction": true,
      "actionable_after_correction": true,
      "dist_to_support": 0.42558135872857034,
      "actionable_reason": "watchlist_correction",
      "priceQuality": {
        "quality_n_bars": 50,
        "long_wick_count": 12,
        "max_long_wicks_allowed": 6,
        "gap_thresh_pct": 2.5,
        "gap_count": 5,
        "max_gap_count_allowed": 2,
        "max_gap_pct": 87.88572038922992,
        "max_gap_pct_allowed": 6.0,
        "avg_volume_50": 2844034,
        "price_quality_ok": false
      },
      "priceQualityOk": false,
      "avgVolume50": 2844034,
      "rank_score": 2.8285664412253717
    },
    {
      "ticker": "ONB",
      "tf": "1d",
      "bars_used": 320,
      "close": 22.899999618530273,
      "sma_fast": 20,
      "sma_slow": 50,
      "sma_fast_now": 22.971500205993653,
      "sma_slow_now": 22.14904365539551,
      "trend_ok": true,
      "recent_swing_high": 23.75,
      "recent_swing_high_date": "2026-01-08",
      "resistance_level": 23.75,
      "pullback_from_swing_high_pct": 3.578948974609375,
      "had_correction": true,
      "bars_since_swing_high": 7,
      "correction_age_ok": true,
      "anchor_support_close": 22.030000686645508,
      "anchor_support_date": "2026-01-02",
      "support_level": 22.030000686645508,
      "support_tolerance_pct": 1.0,
      "support_floor": 22.030000686645508,
      "support_floor_adj": 21.809700679779052,
      "correction_close_low": 22.579999923706055,
      "support_held": true,
      "close_above_sma_fast": false,
      "rebound_ok": false,
      "uptrend_window_used": 50,
      "uptrend_hh_count": 4,
      "uptrend_hl_count": 3,
      "uptrend_pivot_highs": 5,
      "uptrend_pivot_lows": 5,
      "uptrend_overall_up": true,
      "uptrend_ok": true,
      "uptrend_actionable": true,
      "watchlist_correction": true,
      "actionable_after_correction": true,
      "dist_to_support": 0.03949155264494183,
      "actionable_reason": "watchlist_correction",
      "priceQuality": {
        "quality_n_bars": 50,
        "long_wick_count": 12,
        "max_long_wicks_allowed": 6,
        "gap_thresh_pct": 2.5,
        "gap_count": 0,
        "max_gap_count_allowed": 2,
        "max_gap_pct": 1.7316069713469957,
        "max_gap_pct_allowed": 6.0,
        "avg_volume_50": 2697512,
        "price_quality_ok": false
      },
      "priceQualityOk": false,
      "avgVolume50": 2697512,
      "rank_score": 2.768403344815996
    },
    {
      "ticker": "MLTX",
      "tf": "1d",
      "bars_used": 320,
      "close": 16.329999923706055,
      "sma_fast": 20,
      "sma_slow": 50,
      "sma_fast_now": 14.44375,
      "sma_slow_now": 13.786599979400634,
      "trend_ok": true,
      "recent_swing_high": 18.799999237060547,
      "recent_swing_high_date": "2026-01-12",
      "resistance_level": 18.799999237060547,
      "pullback_from_swing_high_pct": 13.13829475314748,
      "had_correction": true,
      "bars_since_swing_high": 5,
      "correction_age_ok": true,
      "anchor_support_close": 11.0600004196167,
      "anchor_support_date": "2026-01-05",
      "support_level": 11.0600004196167,
      "support_tolerance_pct": 1.0,
      "support_floor": 11.0600004196167,
      "support_floor_adj": 10.949400415420532,
      "correction_close_low": 16.329999923706055,
      "support_held": true,
      "close_above_sma_fast": true,
      "rebound_ok": false,
      "uptrend_window_used": 50,
      "uptrend_hh_count": 3,
      "uptrend_hl_count": 3,
      "uptrend_pivot_highs": 6,
      "uptrend_pivot_lows": 6,
      "uptrend_overall_up": true,
      "uptrend_ok": true,
      "uptrend_actionable": true,
      "watchlist_correction": true,
      "actionable_after_correction": true,
      "dist_to_support": 0.47649179965148636,
      "actionable_reason": "watchlist_correction",
      "priceQuality": {
        "quality_n_bars": 50,
        "long_wick_count": 13,
        "max_long_wicks_allowed": 6,
        "gap_thresh_pct": 2.5,
        "gap_count": 3,
        "max_gap_count_allowed": 2,
        "max_gap_pct": 43.401245250317544,
        "max_gap_pct_allowed": 6.0,
        "avg_volume_50": 2606220,
        "price_quality_ok": false
      },
      "priceQualityOk": false,
      "avgVolume50": 2606220,
      "rank_score": 2.7235082003485136
    },
    {
      "ticker": "NYAX",
      "tf": "1d",
      "bars_used": 320,
      "close": 57.939998626708984,
      "sma_fast": 20,
      "sma_slow": 50,
      "sma_fast_now": 52.64755001068115,
      "sma_slow_now": 47.44842025756836,
      "trend_ok": true,
      "recent_swing_high": 59.779998779296875,
      "recent_swing_high_date": "2026-01-14",
      "resistance_level": 59.779998779296875,
      "pullback_from_swing_high_pct": 3.077952810573029,
      "had_correction": true,
      "bars_since_swing_high": 3,
      "correction_age_ok": true,
      "anchor_support_close": 50.79999923706055,
      "anchor_support_date": "2026-01-06",
      "support_level": 50.79999923706055,
      "support_tolerance_pct": 1.0,
      "support_floor": 50.79999923706055,
      "support_floor_adj": 50.29199924468994,
      "correction_close_low": 57.939998626708984,
      "support_held": true,
      "close_above_sma_fast": true,
      "rebound_ok": false,
      "uptrend_window_used": 50,
      "uptrend_hh_count": 3,
      "uptrend_hl_count": 3,
      "uptrend_pivot_highs": 5,
      "uptrend_pivot_lows": 6,
      "uptrend_overall_up": true,
      "uptrend_ok": true,
      "uptrend_actionable": true,
      "watchlist_correction": true,
      "actionable_after_correction": true,
      "dist_to_support": 0.14055117119843447,
      "actionable_reason": "watchlist_correction",
      "priceQuality": {
        "quality_n_bars": 50,
        "long_wick_count": 12,
        "max_long_wicks_allowed": 6,
        "gap_thresh_pct": 2.5,
        "gap_count": 7,
        "max_gap_count_allowed": 2,
        "max_gap_pct": 6.527738776285783,
        "max_gap_pct_allowed": 6.0,
        "avg_volume_50": 12422,
        "price_quality_ok": false
      },
      "priceQualityOk": false,
      "avgVolume50": 12422,
      "rank_score": 2.5672441098588683
    }
  ]
}