{
  "updated_utc": "2026-01-15T22:16:24.788549+00:00",
  "params": {
    "tf": "1d",
    "lookback_days": 520,
    "max_bars": 320,
    "sma_fast": 20,
    "sma_slow": 50,
    "min_pullback_pct": 3.0,
    "swing_window": 80,
    "support_lookback": 80,
    "rebound_bars": 4,
    "support_tolerance_pct": 1.0,
    "uptrend_window_min": 30,
    "uptrend_window_max": 50,
    "pivot_strength": 2,
    "min_hh": 3,
    "min_hl": 3,
    "corr_bars_min": 3,
    "corr_bars_max": 12,
    "only_actionable": false,
    "only_watchlist": true
  },
  "count": 2,
  "data": [
    {
      "ticker": "PNC",
      "tf": "1d",
      "bars_used": 320,
      "close": 212.32000732421875,
      "sma_fast": 20,
      "sma_slow": 50,
      "sma_fast_now": 213.11149978637695,
      "sma_slow_now": 199.97279998779297,
      "trend_ok": true,
      "recent_swing_high": 220.5399932861328,
      "recent_swing_high_date": "2026-01-08",
      "resistance_level": 220.5399932861328,
      "pullback_from_swing_high_pct": 3.727208765826566,
      "had_correction": true,
      "bars_since_swing_high": 4,
      "correction_age_ok": true,
      "anchor_support_close": 208.36000061035156,
      "anchor_support_date": "2026-01-02",
      "support_level": 208.36000061035156,
      "support_tolerance_pct": 1.0,
      "support_floor": 208.36000061035156,
      "support_floor_adj": 206.27640060424804,
      "correction_close_low": 212.32000732421875,
      "support_held": true,
      "close_above_sma_fast": false,
      "rebound_ok": false,
      "uptrend_window_used": 50,
      "uptrend_hh_count": 5,
      "uptrend_hl_count": 3,
      "uptrend_pivot_highs": 6,
      "uptrend_pivot_lows": 6,
      "uptrend_overall_up": true,
      "uptrend_ok": true,
      "uptrend_actionable": true,
      "watchlist_correction": true,
      "actionable_after_correction": true,
      "dist_to_support": 0.0190055994541519,
      "actionable_reason": "watchlist_correction",
      "rank_score": 2.853715277128505
    },
    {
      "ticker": "TRU",
      "tf": "1d",
      "bars_used": 320,
      "close": 85.5,
      "sma_fast": 20,
      "sma_slow": 50,
      "sma_fast_now": 85.68949966430664,
      "sma_slow_now": 83.69776733398437,
      "trend_ok": true,
      "recent_swing_high": 89.12000274658203,
      "recent_swing_high_date": "2026-01-09",
      "resistance_level": 89.12000274658203,
      "pullback_from_swing_high_pct": 4.06194191541457,
      "had_correction": true,
      "bars_since_swing_high": 3,
      "correction_age_ok": true,
      "anchor_support_close": 81.08000183105469,
      "anchor_support_date": "2026-01-06",
      "support_level": 81.08000183105469,
      "support_tolerance_pct": 1.0,
      "support_floor": 81.08000183105469,
      "support_floor_adj": 80.26920181274414,
      "correction_close_low": 83.95999908447266,
      "support_held": true,
      "close_above_sma_fast": false,
      "rebound_ok": false,
      "uptrend_window_used": 50,
      "uptrend_hh_count": 5,
      "uptrend_hl_count": 3,
      "uptrend_pivot_highs": 8,
      "uptrend_pivot_lows": 6,
      "uptrend_overall_up": true,
      "uptrend_ok": true,
      "uptrend_actionable": true,
      "watchlist_correction": true,
      "actionable_after_correction": true,
      "dist_to_support": 0.05451403637305292,
      "actionable_reason": "watchlist_correction",
      "rank_score": 2.8516801551684043
    }
  ]
}