{
  "updated_utc": "2026-01-27T20:13:33.638773+00:00",
  "tf": "1d",
  "params": {
    "pole_bars": 10,
    "flag_bars": 8,
    "min_pole_gain_pct": 10.0,
    "near_breakout_pct": 3.0,
    "flag_pullback_min_pct": 1.0,
    "flag_pullback_max_pct": 8.0,
    "tight_ratio": 0.6,
    "sma_fast": 20,
    "sma_slow": 50
  },
  "count": 1,
  "data": [
    {
      "ticker": "KRISHNADEF.NS",
      "tf": "1d",
      "bars_used": 320,
      "close": 948.25,
      "sma20": 881.7999969482422,
      "sma50": 810.7099975585937,
      "trend_ok": true,
      "pole_bars": 10,
      "pole_gain_pct": 11.126811151538716,
      "pole_high": 1019.0,
      "pole_range": 234.0,
      "flag_bars": 8,
      "flag_range": 115.0,
      "pullback_from_pole_high_pct": 6.943081452404318,
      "pullback_ok": true,
      "tight_ok": true,
      "flag_hold_ok": true,
      "near_breakout": false,
      "pattern": "bull_flag",
      "rank_score": 1.7372522384886167
    }
  ]
}